CHANGELOG.txt
LICENSE.txt
MANIFEST.in
README.txt
setup.py
gbrf/__init__.py
gbrf/gbrf.py
gbrf.egg-info/PKG-INFO
gbrf.egg-info/SOURCES.txt
gbrf.egg-info/dependency_links.txt
gbrf.egg-info/requires.txt
gbrf.egg-info/top_level.txt