Metadata-Version: 2.1
Name: gbrf
Version: 1.0.7
Summary: Gradient Boosted Random Forest Classifier (gbrf)
Home-page: 
Author: Abhishek Singh
Author-email: abhishek.ec@global.org.in
License: MIT
Keywords: machine learning
License-File: LICENSE.txt
